jssl/README.md
jssl/__init__.py
jssl/api.py
jssl/backend.py
jssl/ball.csv
jssl/camera-setting.html
jssl/client.py
jssl/config.py
jssl/control.py
jssl/debug.sh
jssl/demo.sh
jssl/detection.py
jssl/em.py
jssl/field.py
jssl/field_dimensions.py
jssl/game_controller.py
jssl/index.html
jssl/log.csv
jssl/logger.py
jssl/place.py
jssl/robot.html
jssl/robot.py
jssl/robots.py
jssl/team.html
jssl/utils.py
jssl/video.py
jssl/__pycache__/__init__.cpython-38.pyc
jssl/__pycache__/app.cpython-38.pyc
jssl/__pycache__/backend.cpython-38.pyc
jssl/__pycache__/client.cpython-38.pyc
jssl/__pycache__/config.cpython-38.pyc
jssl/__pycache__/control.cpython-38.pyc
jssl/__pycache__/detection.cpython-38.pyc
jssl/__pycache__/em.cpython-38.pyc
jssl/__pycache__/field.cpython-38.pyc
jssl/__pycache__/game_controller.cpython-38.pyc
jssl/__pycache__/goto.cpython-38.pyc
jssl/__pycache__/place.cpython-38.pyc
jssl/__pycache__/robot.cpython-38.pyc
jssl/__pycache__/robots.cpython-38.pyc
jssl/__pycache__/utils.cpython-38.pyc
jssl/__pycache__/video.cpython-38.pyc
jssl/bootstrap/css/bootstrap-grid.css
jssl/bootstrap/css/bootstrap-grid.css.map
jssl/bootstrap/css/bootstrap-grid.min.css
jssl/bootstrap/css/bootstrap-grid.min.css.map
jssl/bootstrap/css/bootstrap-grid.rtl.css
jssl/bootstrap/css/bootstrap-grid.rtl.css.map
jssl/bootstrap/css/bootstrap-grid.rtl.min.css
jssl/bootstrap/css/bootstrap-grid.rtl.min.css.map
jssl/bootstrap/css/bootstrap-reboot.css
jssl/bootstrap/css/bootstrap-reboot.css.map
jssl/bootstrap/css/bootstrap-reboot.min.css
jssl/bootstrap/css/bootstrap-reboot.min.css.map
jssl/bootstrap/css/bootstrap-reboot.rtl.css
jssl/bootstrap/css/bootstrap-reboot.rtl.css.map
jssl/bootstrap/css/bootstrap-reboot.rtl.min.css
jssl/bootstrap/css/bootstrap-reboot.rtl.min.css.map
jssl/bootstrap/css/bootstrap-utilities.css
jssl/bootstrap/css/bootstrap-utilities.css.map
jssl/bootstrap/css/bootstrap-utilities.min.css
jssl/bootstrap/css/bootstrap-utilities.min.css.map
jssl/bootstrap/css/bootstrap-utilities.rtl.css
junior_ssl-0.5.0.dist-info/LICENSE
junior_ssl-0.5.0.dist-info/METADATA
junior_ssl-0.5.0.dist-info/WHEEL
junior_ssl-0.5.0.dist-info/top_level.txt
junior_ssl-0.5.0.dist-info/RECORD
