Metadata-Version: 2.1
Name: junior-ssl
Version: 0.5.0
Summary: Junior SSL - An omniwheel soccer setup
Home-page: https://github.com/rhoban/junior-ssl/
Author: Rhoban team
Author-email: team@rhoban.com
License: UNKNOWN
Keywords: robot holonomic omniwheel ssl robocup junior soccer standard localized tracking
Platform: UNKNOWN
Classifier: Programming Language :: Python :: 3
Classifier: License :: Free for non-commercial use
Classifier: Operating System :: OS Independent
Requires-Python: >=3.6
Requires-Dist: numpy
Requires-Dist: zmq
Provides-Extra: gc
Requires-Dist: flask ; extra == 'gc'
Requires-Dist: flask-cors ; extra == 'gc'
Requires-Dist: opencv-contrib-python-headless ; extra == 'gc'
Requires-Dist: opencv-python-headless ; extra == 'gc'
Requires-Dist: pyserial ; extra == 'gc'
Requires-Dist: waitress ; extra == 'gc'
